[
  {
    "type": "proficiency",
    "id": "prof_maces_familiar",
    "category": "prof_combat",
    "name": { "str": "Mace Familiarity" },
    "description": "You've got the gist of bludgeoning your enemies.",
    "can_learn": true,
    "default_time_multiplier": 1.5,
    "default_skill_penalty": 0.2,
    "bonuses": { "melee_attack": [ { "type": "stamina", "value": 0.025 } ] },
    "//": "Code assumes each attack is 1s",
    "time_to_learn": "800 s"
  },
  {
    "type": "proficiency",
    "id": "prof_maces_pro",
    "category": "prof_combat",
    "name": { "str": "Mace Proficiency" },
    "description": "You swing your mace with dead efficiency.",
    "can_learn": true,
    "default_time_multiplier": 1.5,
    "default_skill_penalty": 0.2,
    "bonuses": { "melee_attack": [ { "type": "stamina", "value": 0.025 } ] },
    "//": "Code assumes each attack is 1s",
    "time_to_learn": "1600 s",
    "required_proficiencies": [ "prof_maces_familiar" ]
  },
  {
    "type": "proficiency",
    "id": "prof_maces_master",
    "category": "prof_combat",
    "name": { "str": "Mace Mastery" },
    "description": "Your strikes with a mace shatter skulls and pulp brains.",
    "can_learn": true,
    "default_time_multiplier": 1.5,
    "default_skill_penalty": 0.2,
    "bonuses": { "melee_attack": [ { "type": "stamina", "value": 0.05 } ] },
    "//": "Code assumes each attack is 1s",
    "time_to_learn": "3200 s",
    "required_proficiencies": [ "prof_maces_pro" ]
  },
  {
    "type": "mutation",
    "id": "WINGS_BUTTERFLY",
    "name": { "str": "Insect Wings" },
    "points": 1,
    "visibility": 4,
    "ugliness": 4,
    "description": "A large pair of translucent wings grow from your back.  They are too small to lift you, but if you're not weighed down, they can help a bit if you fall.  You can flutter them quickly to improve your move speed, but this is noisy and tires you out.",
    "types": [ "WINGS" ],
    "prereqs": [ "WINGS_STUB" ],
    "restricts_gear": [ "torso" ],
    "flags": [ "WINGS_1" ],
    "active": true,
    "valid": false,
    "transform": { "target": "WINGS_INSECT_active", "msg_transform": "You begin buzzing your wings.", "active": true, "moves": 20 }
  },
  {
    "type": "mutation",
    "id": "URSINE_EYE",
    "name": { "str": "Ursine Vision" },
    "description": "Obsoleted Ursine Vision mutation.  Bears now get Mesopic and Night Vision.",
    "points": 0,
    "valid": false,
    "player_display": false
  },
  {
    "type": "mutation",
    "id": "KILLER",
    "name": { "str": "Killer Drive" },
    "description": "Obsoleted Killer Drive mutation.",
    "points": 0,
    "valid": false,
    "player_display": false
  },
  {
    "type": "mutation",
    "id": "MARTIAL_FENCING",
    "name": { "str": "Competitive Fencer" },
    "description": "Obsoleted Competitive Fencer mutation.",
    "points": 0,
    "valid": false,
    "player_display": false
  },
  {
    "type": "mutation",
    "id": "TINYSTOMACH",
    "name": { "str": "Tiny Stomach" },
    "description": "Obsoleted Tiny Stomach mutation.",
    "points": 0,
    "valid": false,
    "player_display": false
  },
  {
    "type": "mutation",
    "id": "MARTIAL_ARTS2",
    "name": { "str": "Self Defense" },
    "description": "Obsoleted Self Defense mutation.",
    "points": 0,
    "valid": false,
    "player_display": false
  },
  {
    "type": "mutation",
    "id": "MARTIAL_ARTS5",
    "name": { "str": "Melee Training" },
    "description": "Obsoleted Melee Martial Arts mutation.",
    "points": 0,
    "valid": false,
    "player_display": false
  },
  {
    "type": "mutation",
    "id": "MARTIAL_ARTS3",
    "name": { "str": "Melee Training" },
    "description": "Obsoleted Melee Martial Arts mutation.",
    "points": 0,
    "valid": false,
    "player_display": false
  },
  {
    "type": "mutation",
    "id": "PROF_MA_ORANGE",
    "name": { "str": "Orange Belt" },
    "description": "Obsoleted Orange Belt mutation.",
    "points": 0,
    "valid": false,
    "player_display": false
  },
  {
    "type": "mutation",
    "id": "PROF_MA_BLACK",
    "name": { "str": "Black Belt" },
    "description": "Obsoleted Black Belt mutation.",
    "points": 0,
    "valid": false,
    "player_display": false
  },
  {
    "type": "mutation",
    "id": "MUT_JUNKIE",
    "name": { "str": "Metallassimophile" },
    "description": "Obsoleted mutation.",
    "points": 0,
    "valid": false,
    "player_display": false
  },
  {
    "type": "mutation",
    "id": "PROF_BOXER",
    "name": { "str": "Boxer" },
    "description": "Obsoleted mutation.",
    "points": 0,
    "valid": false,
    "player_display": false
  },
  {
    "type": "mutation",
    "id": "PROF_KICKBOXER",
    "name": { "str": "Kickboxer" },
    "description": "Obsoleted mutation.",
    "points": 0,
    "valid": false,
    "player_display": false
  },
  {
    "type": "mutation",
    "id": "ARM_TENTACLES_8",
    "name": { "str": "8 Tentacles" },
    "description": "Obsoleted mutation.",
    "points": 0,
    "valid": false,
    "player_display": false
  },
  {
    "type": "mutation",
    "id": "TALONS",
    "name": { "str": "Talons" },
    "description": "Obsoleted mutation.",
    "points": 0,
    "valid": false,
    "player_display": false
  },
  {
    "type": "mutation",
    "id": "CLAWS_ST",
    "name": { "str": "Stainless Claws" },
    "description": "Obsoleted mutation.",
    "points": 0,
    "valid": false,
    "player_display": false
  },
  {
    "type": "mutation",
    "id": "CLAWS_RAT",
    "name": { "str": "Grizzled Claws" },
    "description": "Obsoleted mutation.",
    "points": 0,
    "valid": false,
    "player_display": false
  },
  {
    "type": "mutation",
    "id": "HOARDER",
    "name": { "str": "Hoarder" },
    "description": "Obsoleted mutation.",
    "points": 0,
    "valid": false,
    "player_display": false
  },
  {
    "id": "morale_perm_badtemper",
    "type": "morale_type",
    "text": "Pessimist"
  },
  {
    "type": "mutation",
    "id": "BADTEMPER",
    "name": { "str": "Bad temper" },
    "description": "Renamed/re-IDed mutation.",
    "points": 0,
    "valid": false,
    "player_display": false
  },
  {
    "id": "mon_goose_canadian",
    "type": "MONSTER",
    "copy-from": "mon_goose",
    "name": { "str": "goose", "str_pl": "geese" },
    "looks_like": "mon_goose"
  },
  {
    "id": "mon_goose_canadian_chick",
    "type": "MONSTER",
    "copy-from": "mon_goose_chick",
    "looks_like": "mon_goose_chick"
  },
  {
    "id": "EOC_Nunez_Travel",
    "type": "effect_on_condition"
  },
  {
    "type": "mutation",
    "id": "NO_CBM_INSTALLATION",
    "name": { "str": "Oversensitive System" },
    "description": "Renamed/re-IDed mutation.",
    "points": 0,
    "valid": false,
    "player_display": false
  },
  {
    "type": "mutation",
    "id": "WAYFARER",
    "name": { "str": "Wayfarer" },
    "description": "Removed mutation.",
    "points": 0,
    "valid": false,
    "player_display": false
  },
  {
    "type": "mutation",
    "id": "BRAWLER",
    "name": { "str": "Brawler" },
    "description": "Removed mutation.",
    "points": 0,
    "valid": false,
    "player_display": false
  },
  {
    "type": "effect_on_condition",
    "id": "asphyxiation_to_hypoxia"
  },
  {
    "type": "effect_on_condition",
    "id": "lose_asphyxiation"
  },
  {
    "type": "mutation",
    "id": "FASTLEARNER",
    "name": { "str": "Fast Learner" },
    "points": 0,
    "player_display": false,
    "description": "Obsoleted trait.",
    "random_at_chargen": false,
    "valid": false
  },
    {
    "type": "mutation",
    "id": "PACKMULE",
    "name": { "str": "Pack Mule" },
    "points": 0,
    "player_display": false,
    "description": "Obsoleted trait.",
    "random_at_chargen": false,
    "valid": false
  },
  {
    "type": "mutation",
    "id": "TRUTHTELLER",
    "name": { "str": "Truth Teller" },
    "points": 0,
    "player_display": false,
    "description": "Obsoleted trait.",
    "random_at_chargen": false,
    "valid": false
  },
  {
    "id": "scenario_assassin_convict",
    "type": "effect_on_condition"
  },
  {
    "type": "TRAIT_MIGRATION",
    "id": "PROF_ASSASSIN_CONVICT",
    "remove": true
  },
  {
    "type": "ter_furn_migration",
    "from_furn": "f_arc_furnace",
    "to_furn": "f_arcfurnace_empty"
  },
  {
    "type": "overmap_special_migration",
    "id": "military_outpost_cross",
    "new_id": "military_outpost",
    "//": "Migrated in 0.I"
  },
  {
    "type": "oter_id_migration",
    "//": "migrated in 0.I",
    "oter_ids": {
      "outpost_cross_north": "outpost_north",
      "outpost_cross_south": "outpost_south",
      "outpost_cross_east": "outpost_east",
      "outpost_cross_west": "outpost_west"
    }
  },
  {
    "type": "oter_id_migration",
    "//": "migrated in 0.I",
    "oter_ids": {
      "outpost_cross_roof_north": "outpost_roof_north",
      "outpost_cross_roof_south": "outpost_roof_south",
      "outpost_cross_roof_east": "outpost_roof_east",
      "outpost_cross_roof_west": "outpost_roof_west"
    }
  },
  {
    "id": "waterproof_gunmod",
    "type": "GUNMOD",
    "name": { "str": "firearm waterproofing" },
    "description": "A set of seals and gaskets that will allow a firearm to operate reliably while submerged in water.",
    "weight": "220 g",
    "volume": "250 ml",
    "integral_volume": "0 ml",
    "price": "500 USD",
    "price_postapoc": "7 USD 50 cent",
    "material": [ "plastic" ],
    "symbol": ":",
    "color": "dark_gray",
    "location": "mechanism",
    "mod_targets": [ "smg", "rifle", "pistol", "shotgun", "launcher" ],
    "install_time": "10 m",
    "min_skills": [ [ "weapon", 2 ] ],
    "flags": [ "WATERPROOF_GUN" ]
  },
  {
    "id": "gun_crossbow",
    "type": "GUNMOD",
    "name": { "str": "rail-mounted crossbow" },
    "description": "A kit to attach a pair of crossbow arms and a firing rail to the barrel of a long firearm.  It allows crossbow bolts to be fired.",
    "weight": "1450 g",
    "volume": "500 ml",
    "price": "500 USD",
    "price_postapoc": "15 USD",
    "install_time": "30 m",
    "material": [ "steel", "wood" ],
    "symbol": ":",
    "color": "light_red",
    "location": "rail",
    "mod_targets": [ "shotgun", "rifle", "crossbow" ],
    "gun_data": {
      "ammo": [ "bolt" ],
      "skill": "rifle",
      "range": 8,
      "ranged_damage": { "damage_type": "stab", "amount": 3 },
      "dispersion": 180,
      "durability": 10,
      "clip_size": 1
    },
    "dispersion_modifier": 60,
    "min_skills": [ [ "weapon", 2 ], [ "rifle", 1 ] ],
    "flags": [ "PRIMITIVE_RANGED_WEAPON", "NON_FOULING" ],
    "pocket_data": [ { "pocket_type": "MAGAZINE", "ammo_restriction": { "bolt": 1 } } ]
  },
  {
    "id": "makeshift_bayonet",
    "copy-from": "spike",
    "type": "GENERIC",
    "name": { "str": "makeshift bayonet" },
    "description": "A makeshift version of a bayonet that consists of a mere spike with some string.",
    "longest_side": "12 cm",
    "integral_longest_side": "12 cm",
    "gunmod_data": {
      "location": "underbarrel",
      "mod_targets": [ "shotgun", "rifle", "smg", "launcher", "crossbow" ],
      "is_bayonet": true,
      "blacklist_mod": [ "knife_combat_army", "knife_combat", "enfield_bayonet", "knife_combat_marine", "makeshift_bayonet", "sword_bayonet" ],
      "install_time": "5 m"
    },
    "extend": { "flags": [ "PUMP_RAIL_COMPATIBLE" ] }
  }
]
